[
    {
        "overview": {
            "game_date": 1697875200.0,
            "url": "https://www.bet365.com/#/AC/B151/C20902720/D19/E18151442/F19/",
            "league": "LOL - World Champs",
            "home_team": "JD Gaming",
            "away_team": "LNG Esports"
        },
        "winner": [
            {
                "total_amount": -1.0,
                "home_team_score": 1.44,
                "away_team_score": 2.62
            }
        ],
        "first_blood": [
            {
                "total_amount": 1.0,
                "home_team_score": 1.72,
                "away_team_score": 2.0
            }
        ],
        "first_kill_baron": [
            {
                "total_amount": 1.0,
                "home_team_score": 1.57,
                "away_team_score": 2.25
            }
        ],
        "first_destroy_inhibitor": [
            {
                "total_amount": 1.0,
                "home_team_score": 1.5,
                "away_team_score": 2.5
            }
        ],
        "kill_handicap": [
            {
                "total_amount": 6.5,
                "home_team_score": 1.83,
                "away_team_score": 1.83
            }
        ],
        "total_kills": [
            {
                "total_amount": 24.5,
                "home_team_score": 1.83,
                "away_team_score": 1.83
            }
        ],
        "total_towers": [
            {
                "total_amount": 12.5,
                "home_team_score": 2.1,
                "away_team_score": 1.66
            }
        ],
        "tower_handicap": [],
        "first_tower": [],
        "total_dragons": [
            {
                "total_amount": 4.5,
                "home_team_score": 2.2,
                "away_team_score": 1.61
            }
        ],
        "first_dragon": [],
        "total_barons": [
            {
                "total_amount": 1.5,
                "home_team_score": 1.9,
                "away_team_score": 1.8
            }
        ],
        "total_inhibitors": [
            {
                "total_amount": 1.5,
                "home_team_score": 1.8,
                "away_team_score": 1.9
            }
        ],
        "game_duration": [
            {
                "total_amount": 30.5,
                "home_team_score": 1.83,
                "away_team_score": 1.83
            }
        ]
    },
    {
        "overview": {
            "game_date": 1697886000.0,
            "url": "https://www.bet365.com/#/AC/B151/C20902720/D19/E18151441/F19/",
            "league": "LOL - World Champs",
            "home_team": "G2 Esports",
            "away_team": "Gen.G"
        },
        "winner": [
            {
                "total_amount": -1.0,
                "home_team_score": 3.5,
                "away_team_score": 1.28
            }
        ],
        "first_blood": [
            {
                "total_amount": 1.0,
                "home_team_score": 2.1,
                "away_team_score": 1.66
            }
        ],
        "first_kill_baron": [
            {
                "total_amount": 1.0,
                "home_team_score": 2.75,
                "away_team_score": 1.4
            }
        ],
        "first_destroy_inhibitor": [
            {
                "total_amount": 1.0,
                "home_team_score": 3.4,
                "away_team_score": 1.3
            }
        ],
        "kill_handicap": [
            {
                "total_amount": 7.5,
                "home_team_score": 1.83,
                "away_team_score": 1.83
            }
        ],
        "total_kills": [
            {
                "total_amount": 25.5,
                "home_team_score": 1.83,
                "away_team_score": 1.83
            }
        ],
        "total_towers": [
            {
                "total_amount": 12.5,
                "home_team_score": 2.1,
                "away_team_score": 1.66
            }
        ],
        "tower_handicap": [],
        "first_tower": [],
        "total_dragons": [
            {
                "total_amount": 4.5,
                "home_team_score": 2.25,
                "away_team_score": 1.57
            }
        ],
        "first_dragon": [],
        "total_barons": [
            {
                "total_amount": 1.5,
                "home_team_score": 2.1,
                "away_team_score": 1.66
            }
        ],
        "total_inhibitors": [
            {
                "total_amount": 1.5,
                "home_team_score": 1.8,
                "away_team_score": 1.9
            }
        ],
        "game_duration": [
            {
                "total_amount": 29.5,
                "home_team_score": 1.83,
                "away_team_score": 1.83
            }
        ]
    },
    {
        "overview": {
            "game_date": 1697961600.0,
            "url": "https://www.bet365.com/#/AC/B151/C20902720/D19/E18151444/F19/",
            "league": "LOL - World Champs",
            "home_team": "T1",
            "away_team": "Cloud9"
        },
        "winner": [],
        "first_blood": [
            {
                "total_amount": 1.0,
                "home_team_score": 1.61,
                "away_team_score": 2.2
            }
        ],
        "first_kill_baron": [
            {
                "total_amount": 1.0,
                "home_team_score": 1.3,
                "away_team_score": 3.4
            }
        ],
        "first_destroy_inhibitor": [
            {
                "total_amount": 1.0,
                "home_team_score": 1.2,
                "away_team_score": 4.33
            }
        ],
        "kill_handicap": [
            {
                "total_amount": 8.5,
                "home_team_score": 1.8,
                "away_team_score": 1.9
            }
        ],
        "total_kills": [
            {
                "total_amount": 23.5,
                "home_team_score": 1.8,
                "away_team_score": 1.9
            }
        ],
        "total_towers": [
            {
                "total_amount": 11.5,
                "home_team_score": 1.72,
                "away_team_score": 2.0
            }
        ],
        "tower_handicap": [],
        "first_tower": [],
        "total_dragons": [
            {
                "total_amount": 3.5,
                "home_team_score": 1.4,
                "away_team_score": 2.75
            }
        ],
        "first_dragon": [],
        "total_barons": [
            {
                "total_amount": 1.5,
                "home_team_score": 2.75,
                "away_team_score": 1.4
            }
        ],
        "total_inhibitors": [
            {
                "total_amount": 1.5,
                "home_team_score": 1.8,
                "away_team_score": 1.9
            }
        ],
        "game_duration": [
            {
                "total_amount": 30.5,
                "home_team_score": 1.83,
                "away_team_score": 1.83
            }
        ]
    },
    {
        "overview": {
            "game_date": 1697965200.0,
            "url": "https://www.bet365.com/#/AC/B151/C20902720/D19/E18151443/F19/",
            "league": "LOL - World Champs",
            "home_team": "NRG",
            "away_team": "MAD Lions"
        },
        "winner": [],
        "first_blood": [
            {
                "total_amount": 1.0,
                "home_team_score": 1.9,
                "away_team_score": 1.8
            }
        ],
        "first_kill_baron": [
            {
                "total_amount": 1.0,
                "home_team_score": 2.0,
                "away_team_score": 1.72
            }
        ],
        "first_destroy_inhibitor": [
            {
                "total_amount": 1.0,
                "home_team_score": 2.1,
                "away_team_score": 1.66
            }
        ],
        "kill_handicap": [
            {
                "total_amount": 4.5,
                "home_team_score": 1.83,
                "away_team_score": 1.83
            }
        ],
        "total_kills": [
            {
                "total_amount": 24.5,
                "home_team_score": 1.83,
                "away_team_score": 1.83
            }
        ],
        "total_towers": [
            {
                "total_amount": 12.5,
                "home_team_score": 1.66,
                "away_team_score": 2.1
            }
        ],
        "tower_handicap": [],
        "first_tower": [],
        "total_dragons": [
            {
                "total_amount": 4.5,
                "home_team_score": 1.83,
                "away_team_score": 1.83
            }
        ],
        "first_dragon": [],
        "total_barons": [
            {
                "total_amount": 1.5,
                "home_team_score": 1.72,
                "away_team_score": 2.0
            }
        ],
        "total_inhibitors": [
            {
                "total_amount": 1.5,
                "home_team_score": 1.8,
                "away_team_score": 1.9
            }
        ],
        "game_duration": [
            {
                "total_amount": 32.5,
                "home_team_score": 1.83,
                "away_team_score": 1.83
            }
        ]
    },
    {
        "overview": {
            "game_date": 1697968800.0,
            "url": "https://www.bet365.com/#/AC/B151/C20902720/D19/E18151446/F19/",
            "league": "LOL - World Champs",
            "home_team": "Bilibili Gaming",
            "away_team": "Fnatic"
        },
        "winner": [],
        "first_blood": [
            {
                "total_amount": 1.0,
                "home_team_score": 1.61,
                "away_team_score": 2.2
            }
        ],
        "first_kill_baron": [
            {
                "total_amount": 1.0,
                "home_team_score": 1.3,
                "away_team_score": 3.4
            }
        ],
        "first_destroy_inhibitor": [
            {
                "total_amount": 1.0,
                "home_team_score": 1.2,
                "away_team_score": 4.33
            }
        ],
        "kill_handicap": [
            {
                "total_amount": 8.5,
                "home_team_score": 1.83,
                "away_team_score": 1.83
            }
        ],
        "total_kills": [
            {
                "total_amount": 25.5,
                "home_team_score": 1.83,
                "away_team_score": 1.83
            }
        ],
        "total_towers": [
            {
                "total_amount": 11.5,
                "home_team_score": 1.72,
                "away_team_score": 2.0
            }
        ],
        "tower_handicap": [],
        "first_tower": [],
        "total_dragons": [
            {
                "total_amount": 3.5,
                "home_team_score": 1.4,
                "away_team_score": 2.75
            }
        ],
        "first_dragon": [],
        "total_barons": [
            {
                "total_amount": 1.5,
                "home_team_score": 2.75,
                "away_team_score": 1.4
            }
        ],
        "total_inhibitors": [
            {
                "total_amount": 1.5,
                "home_team_score": 1.8,
                "away_team_score": 1.9
            }
        ],
        "game_duration": [
            {
                "total_amount": 30.5,
                "home_team_score": 1.83,
                "away_team_score": 1.83
            }
        ]
    },
    {
        "overview": {
            "game_date": 1697972400.0,
            "url": "https://www.bet365.com/#/AC/B151/C20902720/D19/E18151445/F19/",
            "league": "LOL - World Champs",
            "home_team": "KT Rolster",
            "away_team": "Weibo Gaming"
        },
        "winner": [],
        "first_blood": [
            {
                "total_amount": 1.0,
                "home_team_score": 1.83,
                "away_team_score": 1.83
            }
        ],
        "first_kill_baron": [
            {
                "total_amount": 1.0,
                "home_team_score": 1.8,
                "away_team_score": 1.9
            }
        ],
        "first_destroy_inhibitor": [
            {
                "total_amount": 1.0,
                "home_team_score": 1.8,
                "away_team_score": 1.9
            }
        ],
        "kill_handicap": [
            {
                "total_amount": 3.5,
                "home_team_score": 1.83,
                "away_team_score": 1.83
            }
        ],
        "total_kills": [
            {
                "total_amount": 25.5,
                "home_team_score": 1.9,
                "away_team_score": 1.8
            }
        ],
        "total_towers": [
            {
                "total_amount": 12.5,
                "home_team_score": 1.66,
                "away_team_score": 2.1
            }
        ],
        "tower_handicap": [],
        "first_tower": [],
        "total_dragons": [
            {
                "total_amount": 4.5,
                "home_team_score": 1.83,
                "away_team_score": 1.83
            }
        ],
        "first_dragon": [],
        "total_barons": [
            {
                "total_amount": 1.5,
                "home_team_score": 1.72,
                "away_team_score": 2.0
            }
        ],
        "total_inhibitors": [
            {
                "total_amount": 1.5,
                "home_team_score": 1.8,
                "away_team_score": 1.9
            }
        ],
        "game_duration": [
            {
                "total_amount": 31.5,
                "home_team_score": 1.83,
                "away_team_score": 1.83
            }
        ]
    },
    {
        "overview": {
            "game_date": 1698048000.0,
            "url": "https://www.bet365.com/#/AC/B151/C20902720/D19/E18151448/F19/",
            "league": "LOL - World Champs",
            "home_team": "GAM Esports",
            "away_team": "Team Liquid"
        },
        "winner": [
            {
                "total_amount": -1.0,
                "home_team_score": 3.4,
                "away_team_score": 1.3
            }
        ],
        "first_blood": [
            {
                "total_amount": 1.0,
                "home_team_score": 2.1,
                "away_team_score": 1.66
            }
        ],
        "first_kill_baron": [
            {
                "total_amount": 1.0,
                "home_team_score": 2.62,
                "away_team_score": 1.44
            }
        ],
        "first_destroy_inhibitor": [
            {
                "total_amount": 1.0,
                "home_team_score": 3.25,
                "away_team_score": 1.33
            }
        ],
        "kill_handicap": [
            {
                "total_amount": 7.5,
                "home_team_score": 1.83,
                "away_team_score": 1.83
            }
        ],
        "total_kills": [
            {
                "total_amount": 27.5,
                "home_team_score": 1.83,
                "away_team_score": 1.83
            }
        ],
        "total_towers": [
            {
                "total_amount": 12.5,
                "home_team_score": 2.25,
                "away_team_score": 1.57
            }
        ],
        "tower_handicap": [],
        "first_tower": [],
        "total_dragons": [
            {
                "total_amount": 4.5,
                "home_team_score": 2.25,
                "away_team_score": 1.57
            }
        ],
        "first_dragon": [],
        "total_barons": [
            {
                "total_amount": 1.5,
                "home_team_score": 2.25,
                "away_team_score": 1.57
            }
        ],
        "total_inhibitors": [
            {
                "total_amount": 1.5,
                "home_team_score": 1.8,
                "away_team_score": 1.9
            }
        ],
        "game_duration": [
            {
                "total_amount": 29.5,
                "home_team_score": 1.83,
                "away_team_score": 1.83
            }
        ]
    },
    {
        "overview": {
            "game_date": 1698058800.0,
            "url": "https://www.bet365.com/#/AC/B151/C20902720/D19/E18151447/F19/",
            "league": "LOL - World Champs",
            "home_team": "Dplus KIA",
            "away_team": "Team BDS"
        },
        "winner": [
            {
                "total_amount": -1.0,
                "home_team_score": 1.2,
                "away_team_score": 4.33
            }
        ],
        "first_blood": [
            {
                "total_amount": 1.0,
                "home_team_score": 1.61,
                "away_team_score": 2.2
            }
        ],
        "first_kill_baron": [
            {
                "total_amount": 1.0,
                "home_team_score": 1.33,
                "away_team_score": 3.25
            }
        ],
        "first_destroy_inhibitor": [
            {
                "total_amount": 1.0,
                "home_team_score": 1.22,
                "away_team_score": 4.0
            }
        ],
        "kill_handicap": [
            {
                "total_amount": 8.5,
                "home_team_score": 1.83,
                "away_team_score": 1.83
            }
        ],
        "total_kills": [
            {
                "total_amount": 23.5,
                "home_team_score": 1.83,
                "away_team_score": 1.83
            }
        ],
        "total_towers": [
            {
                "total_amount": 11.5,
                "home_team_score": 1.72,
                "away_team_score": 2.0
            }
        ],
        "tower_handicap": [],
        "first_tower": [],
        "total_dragons": [
            {
                "total_amount": 3.5,
                "home_team_score": 1.36,
                "away_team_score": 3.0
            }
        ],
        "first_dragon": [],
        "total_barons": [
            {
                "total_amount": 1.5,
                "home_team_score": 2.75,
                "away_team_score": 1.4
            }
        ],
        "total_inhibitors": [
            {
                "total_amount": 1.5,
                "home_team_score": 1.8,
                "away_team_score": 1.9
            }
        ],
        "game_duration": [
            {
                "total_amount": 30.5,
                "home_team_score": 1.83,
                "away_team_score": 1.83
            }
        ]
    },
    {
        "overview": {
            "game_date": 1698166800.0,
            "url": "https://www.bet365.com/#/AC/B151/C20918935/D19/E18140958/F19/",
            "league": "LOL - Prime Pokal",
            "home_team": "big",
            "away_team": "Eintracht Spandau"
        },
        "winner": [
            {
                "total_amount": -1.0,
                "home_team_score": 2.5,
                "away_team_score": 1.5
            }
        ],
        "first_blood": [
            {
                "total_amount": 1.0,
                "home_team_score": 2.0,
                "away_team_score": 1.72
            }
        ],
        "first_kill_baron": [
            {
                "total_amount": 1.0,
                "home_team_score": 2.25,
                "away_team_score": 1.57
            }
        ],
        "first_destroy_inhibitor": [
            {
                "total_amount": 1.0,
                "home_team_score": 2.5,
                "away_team_score": 1.5
            }
        ],
        "kill_handicap": [
            {
                "total_amount": 7.5,
                "home_team_score": 1.83,
                "away_team_score": 1.83
            }
        ],
        "total_kills": [
            {
                "total_amount": 30.5,
                "home_team_score": 1.83,
                "away_team_score": 1.83
            }
        ],
        "total_towers": [
            {
                "total_amount": 12.5,
                "home_team_score": 2.1,
                "away_team_score": 1.66
            }
        ],
        "tower_handicap": [],
        "first_tower": [],
        "total_dragons": [
            {
                "total_amount": 4.5,
                "home_team_score": 1.9,
                "away_team_score": 1.8
            }
        ],
        "first_dragon": [],
        "total_barons": [
            {
                "total_amount": 1.5,
                "home_team_score": 2.0,
                "away_team_score": 1.72
            }
        ],
        "total_inhibitors": [
            {
                "total_amount": 1.5,
                "home_team_score": 1.57,
                "away_team_score": 2.25
            }
        ],
        "game_duration": [
            {
                "total_amount": 31.5,
                "home_team_score": 1.83,
                "away_team_score": 1.83
            }
        ]
    },
    {
        "overview": {
            "game_date": 1698253200.0,
            "url": "https://www.bet365.com/#/AC/B151/C20918935/D19/E18140955/F19/",
            "league": "LOL - Prime Pokal",
            "home_team": "Unicorns of Love SE",
            "away_team": "MOUZ"
        },
        "winner": [
            {
                "total_amount": -1.0,
                "home_team_score": 1.4,
                "away_team_score": 2.75
            }
        ],
        "first_blood": [
            {
                "total_amount": 1.0,
                "home_team_score": 1.72,
                "away_team_score": 2.0
            }
        ],
        "first_kill_baron": [
            {
                "total_amount": 1.0,
                "home_team_score": 1.53,
                "away_team_score": 2.37
            }
        ],
        "first_destroy_inhibitor": [
            {
                "total_amount": 1.0,
                "home_team_score": 1.44,
                "away_team_score": 2.62
            }
        ],
        "kill_handicap": [
            {
                "total_amount": 7.5,
                "home_team_score": 1.83,
                "away_team_score": 1.83
            }
        ],
        "total_kills": [
            {
                "total_amount": 28.5,
                "home_team_score": 1.83,
                "away_team_score": 1.83
            }
        ],
        "total_towers": [
            {
                "total_amount": 12.5,
                "home_team_score": 2.25,
                "away_team_score": 1.57
            }
        ],
        "tower_handicap": [],
        "first_tower": [],
        "total_dragons": [
            {
                "total_amount": 4.5,
                "home_team_score": 2.25,
                "away_team_score": 1.57
            }
        ],
        "first_dragon": [],
        "total_barons": [
            {
                "total_amount": 1.5,
                "home_team_score": 2.2,
                "away_team_score": 1.61
            }
        ],
        "total_inhibitors": [
            {
                "total_amount": 1.5,
                "home_team_score": 1.57,
                "away_team_score": 2.25
            }
        ],
        "game_duration": [
            {
                "total_amount": 30.5,
                "home_team_score": 1.83,
                "away_team_score": 1.83
            }
        ]
    },
    {
        "overview": {
            "game_date": 1698166800.0,
            "url": "https://www.bet365.com/#/AC/B151/C20916663/D19/E18069597/F19/",
            "league": "LOL - Iberian Cup",
            "home_team": "KOI Academy",
            "away_team": "Biteway Esports"
        },
        "winner": [
            {
                "total_amount": -1.0,
                "home_team_score": 1.16,
                "away_team_score": 4.5
            }
        ],
        "first_blood": [],
        "first_kill_baron": [],
        "first_destroy_inhibitor": [],
        "kill_handicap": [],
        "total_kills": [],
        "total_towers": [],
        "tower_handicap": [],
        "first_tower": [],
        "total_dragons": [],
        "first_dragon": [],
        "total_barons": [],
        "total_inhibitors": [],
        "game_duration": []
    },
    {
        "overview": {
            "game_date": 1698177600.0,
            "url": "https://www.bet365.com/#/AC/B151/C20916663/D19/E18069572/F19/",
            "league": "LOL - Iberian Cup",
            "home_team": "UCAM Tokiers",
            "away_team": "Ramboot Club"
        },
        "winner": [
            {
                "total_amount": -1.0,
                "home_team_score": 1.25,
                "away_team_score": 3.75
            }
        ],
        "first_blood": [],
        "first_kill_baron": [],
        "first_destroy_inhibitor": [],
        "kill_handicap": [],
        "total_kills": [],
        "total_towers": [],
        "tower_handicap": [],
        "first_tower": [],
        "total_dragons": [],
        "first_dragon": [],
        "total_barons": [],
        "total_inhibitors": [],
        "game_duration": []
    },
    {
        "overview": {
            "game_date": 1698253200.0,
            "url": "https://www.bet365.com/#/AC/B151/C20916663/D19/E18133550/F19/",
            "league": "LOL - Iberian Cup",
            "home_team": "Los Heretics",
            "away_team": "Wizards"
        },
        "winner": [
            {
                "total_amount": -1.0,
                "home_team_score": 1.083,
                "away_team_score": 7.0
            }
        ],
        "first_blood": [],
        "first_kill_baron": [],
        "first_destroy_inhibitor": [],
        "kill_handicap": [],
        "total_kills": [],
        "total_towers": [],
        "tower_handicap": [],
        "first_tower": [],
        "total_dragons": [],
        "first_dragon": [],
        "total_barons": [],
        "total_inhibitors": [],
        "game_duration": []
    },
    {
        "overview": {
            "game_date": 1698264000.0,
            "url": "https://www.bet365.com/#/AC/B151/C20916663/D19/E18069574/F19/",
            "league": "LOL - Iberian Cup",
            "home_team": "Rebels Gaming",
            "away_team": "White Dragons"
        },
        "winner": [
            {
                "total_amount": -1.0,
                "home_team_score": 1.2,
                "away_team_score": 4.33
            }
        ],
        "first_blood": [],
        "first_kill_baron": [],
        "first_destroy_inhibitor": [],
        "kill_handicap": [],
        "total_kills": [],
        "total_towers": [],
        "tower_handicap": [],
        "first_tower": [],
        "total_dragons": [],
        "first_dragon": [],
        "total_barons": [],
        "total_inhibitors": [],
        "game_duration": []
    },
    {
        "overview": {
            "game_date": 1698775200.0,
            "url": "https://www.bet365.com/#/AC/B151/C20916663/D19/E18135097/F19/",
            "league": "LOL - Iberian Cup",
            "home_team": "Movistar Riders",
            "away_team": "Kawaii Kiwis"
        },
        "winner": [
            {
                "total_amount": -1.0,
                "home_team_score": 1.03,
                "away_team_score": 10.0
            }
        ],
        "first_blood": [],
        "first_kill_baron": [],
        "first_destroy_inhibitor": [],
        "kill_handicap": [],
        "total_kills": [],
        "total_towers": [],
        "tower_handicap": [],
        "first_tower": [],
        "total_dragons": [],
        "first_dragon": [],
        "total_barons": [],
        "total_inhibitors": [],
        "game_duration": []
    },
    {
        "overview": {
            "game_date": 1698861600.0,
            "url": "https://www.bet365.com/#/AC/B151/C20913138/D19/E18052644/F19/",
            "league": "LOL - Coupe de France",
            "home_team": "Team GO",
            "away_team": "Team Du Sud"
        },
        "winner": [
            {
                "total_amount": -1.0,
                "home_team_score": 1.57,
                "away_team_score": 2.25
            }
        ],
        "first_blood": [
            {
                "total_amount": 1.0,
                "home_team_score": 1.8,
                "away_team_score": 1.9
            }
        ],
        "first_kill_baron": [
            {
                "total_amount": 1.0,
                "home_team_score": 1.66,
                "away_team_score": 2.1
            }
        ],
        "first_destroy_inhibitor": [
            {
                "total_amount": 1.0,
                "home_team_score": 1.57,
                "away_team_score": 2.25
            }
        ],
        "kill_handicap": [
            {
                "total_amount": 6.5,
                "home_team_score": 1.83,
                "away_team_score": 1.83
            }
        ],
        "total_kills": [
            {
                "total_amount": 31.5,
                "home_team_score": 1.83,
                "away_team_score": 1.83
            }
        ],
        "total_towers": [
            {
                "total_amount": 11.5,
                "home_team_score": 2.25,
                "away_team_score": 1.57
            }
        ],
        "tower_handicap": [],
        "first_tower": [],
        "total_dragons": [
            {
                "total_amount": 4.5,
                "home_team_score": 2.37,
                "away_team_score": 1.53
            }
        ],
        "first_dragon": [],
        "total_barons": [
            {
                "total_amount": 1.5,
                "home_team_score": 2.5,
                "away_team_score": 1.5
            }
        ],
        "total_inhibitors": [
            {
                "total_amount": 1.5,
                "home_team_score": 1.61,
                "away_team_score": 2.2
            }
        ],
        "game_duration": [
            {
                "total_amount": 29.5,
                "home_team_score": 1.83,
                "away_team_score": 1.83
            }
        ]
    }
]