[
    {
        "overview": {
            "game_date": 1706691600.0,
            "url": "https://www.bet365.com/#/AC/B151/C20930782/D19/E18901485/F19/",
            "league": "LOL - LCK Spring",
            "home_team": "Kwangdong Freecs",
            "away_team": "Dplus KIA"
        },
        "winner": [
            {
                "total_amount": -1.0,
                "home_team_score": 3.25,
                "away_team_score": 1.33
            }
        ],
        "first_blood": [
            {
                "total_amount": 1.0,
                "home_team_score": 2.0,
                "away_team_score": 1.72
            }
        ],
        "first_kill_baron": [
            {
                "total_amount": 1.0,
                "home_team_score": 2.62,
                "away_team_score": 1.44
            }
        ],
        "first_destroy_inhibitor": [
            {
                "total_amount": 1.0,
                "home_team_score": 3.0,
                "away_team_score": 1.36
            }
        ],
        "kill_handicap": [
            {
                "total_amount": 7.5,
                "home_team_score": 1.83,
                "away_team_score": 1.83
            }
        ],
        "total_kills": [
            {
                "total_amount": 23.5,
                "home_team_score": 1.83,
                "away_team_score": 1.83
            }
        ],
        "total_towers": [
            {
                "total_amount": 11.5,
                "home_team_score": 1.66,
                "away_team_score": 2.1
            }
        ],
        "tower_handicap": [],
        "first_tower": [],
        "total_dragons": [
            {
                "total_amount": 4.5,
                "home_team_score": 2.1,
                "away_team_score": 1.66
            }
        ],
        "first_dragon": [],
        "total_barons": [
            {
                "total_amount": 1.5,
                "home_team_score": 2.25,
                "away_team_score": 1.57
            }
        ],
        "total_inhibitors": [
            {
                "total_amount": 1.5,
                "home_team_score": 1.83,
                "away_team_score": 1.83
            }
        ],
        "game_duration": [
            {
                "total_amount": 32.5,
                "home_team_score": 1.83,
                "away_team_score": 1.83
            }
        ]
    },
    {
        "overview": {
            "game_date": 1706700600.0,
            "url": "https://www.bet365.com/#/AC/B151/C20930782/D19/E18901486/F19/",
            "league": "LOL - LCK Spring",
            "home_team": "KT Rolster",
            "away_team": "OKSavingsBank BRION"
        },
        "winner": [
            {
                "total_amount": -1.0,
                "home_team_score": 1.36,
                "away_team_score": 3.0
            }
        ],
        "first_blood": [
            {
                "total_amount": 1.0,
                "home_team_score": 1.72,
                "away_team_score": 2.0
            }
        ],
        "first_kill_baron": [
            {
                "total_amount": 1.0,
                "home_team_score": 1.5,
                "away_team_score": 2.5
            }
        ],
        "first_destroy_inhibitor": [
            {
                "total_amount": 1.0,
                "home_team_score": 1.4,
                "away_team_score": 2.75
            }
        ],
        "kill_handicap": [
            {
                "total_amount": 6.5,
                "home_team_score": 1.83,
                "away_team_score": 1.83
            }
        ],
        "total_kills": [
            {
                "total_amount": 23.5,
                "home_team_score": 1.83,
                "away_team_score": 1.83
            }
        ],
        "total_towers": [
            {
                "total_amount": 11.5,
                "home_team_score": 1.83,
                "away_team_score": 1.83
            }
        ],
        "tower_handicap": [],
        "first_tower": [],
        "total_dragons": [
            {
                "total_amount": 4.5,
                "home_team_score": 2.1,
                "away_team_score": 1.66
            }
        ],
        "first_dragon": [],
        "total_barons": [
            {
                "total_amount": 1.5,
                "home_team_score": 2.2,
                "away_team_score": 1.61
            }
        ],
        "total_inhibitors": [
            {
                "total_amount": 1.5,
                "home_team_score": 1.53,
                "away_team_score": 2.37
            }
        ],
        "game_duration": [
            {
                "total_amount": 32.5,
                "home_team_score": 1.83,
                "away_team_score": 1.83
            }
        ]
    },
    {
        "overview": {
            "game_date": 1706778000.0,
            "url": "https://www.bet365.com/#/AC/B151/C20930782/D19/E18901488/F19/",
            "league": "LOL - LCK Spring",
            "home_team": "T1",
            "away_team": "DRX"
        },
        "winner": [
            {
                "total_amount": -1.0,
                "home_team_score": 1.57,
                "away_team_score": 2.25
            }
        ],
        "first_blood": [
            {
                "total_amount": 1.0,
                "home_team_score": 1.8,
                "away_team_score": 1.9
            }
        ],
        "first_kill_baron": [
            {
                "total_amount": 1.0,
                "home_team_score": 1.66,
                "away_team_score": 2.1
            }
        ],
        "first_destroy_inhibitor": [
            {
                "total_amount": 1.0,
                "home_team_score": 1.57,
                "away_team_score": 2.25
            }
        ],
        "kill_handicap": [
            {
                "total_amount": 5.5,
                "home_team_score": 1.83,
                "away_team_score": 1.83
            }
        ],
        "total_kills": [
            {
                "total_amount": 22.5,
                "home_team_score": 1.83,
                "away_team_score": 1.83
            }
        ],
        "total_towers": [
            {
                "total_amount": 12.5,
                "home_team_score": 2.1,
                "away_team_score": 1.66
            }
        ],
        "tower_handicap": [],
        "first_tower": [],
        "total_dragons": [
            {
                "total_amount": 4.5,
                "home_team_score": 1.53,
                "away_team_score": 2.37
            }
        ],
        "first_dragon": [],
        "total_barons": [
            {
                "total_amount": 1.5,
                "home_team_score": 1.8,
                "away_team_score": 1.9
            }
        ],
        "total_inhibitors": [
            {
                "total_amount": 1.5,
                "home_team_score": 1.5,
                "away_team_score": 2.5
            }
        ],
        "game_duration": [
            {
                "total_amount": 33.5,
                "home_team_score": 1.83,
                "away_team_score": 1.83
            }
        ]
    },
    {
        "overview": {
            "game_date": 1706787000.0,
            "url": "https://www.bet365.com/#/AC/B151/C20930782/D19/E18901488/F19/",
            "league": "LOL - LCK Spring",
            "home_team": "FearX",
            "away_team": "Nongshim RedForce"
        },
        "winner": [
            {
                "total_amount": -1.0,
                "home_team_score": 1.57,
                "away_team_score": 2.25
            }
        ],
        "first_blood": [
            {
                "total_amount": 1.0,
                "home_team_score": 1.8,
                "away_team_score": 1.9
            }
        ],
        "first_kill_baron": [
            {
                "total_amount": 1.0,
                "home_team_score": 1.66,
                "away_team_score": 2.1
            }
        ],
        "first_destroy_inhibitor": [
            {
                "total_amount": 1.0,
                "home_team_score": 1.57,
                "away_team_score": 2.25
            }
        ],
        "kill_handicap": [
            {
                "total_amount": 5.5,
                "home_team_score": 1.83,
                "away_team_score": 1.83
            }
        ],
        "total_kills": [
            {
                "total_amount": 22.5,
                "home_team_score": 1.83,
                "away_team_score": 1.83
            }
        ],
        "total_towers": [
            {
                "total_amount": 12.5,
                "home_team_score": 2.1,
                "away_team_score": 1.66
            }
        ],
        "tower_handicap": [],
        "first_tower": [],
        "total_dragons": [
            {
                "total_amount": 4.5,
                "home_team_score": 1.53,
                "away_team_score": 2.37
            }
        ],
        "first_dragon": [],
        "total_barons": [
            {
                "total_amount": 1.5,
                "home_team_score": 1.8,
                "away_team_score": 1.9
            }
        ],
        "total_inhibitors": [
            {
                "total_amount": 1.5,
                "home_team_score": 1.5,
                "away_team_score": 2.5
            }
        ],
        "game_duration": [
            {
                "total_amount": 33.5,
                "home_team_score": 1.83,
                "away_team_score": 1.83
            }
        ]
    },
    {
        "overview": {
            "game_date": 1706864400.0,
            "url": "https://www.bet365.com/#/AC/B151/C20930782/D19/E18901489/F19/",
            "league": "LOL - LCK Spring",
            "home_team": "Gen.G",
            "away_team": "Kwangdong Freecs"
        },
        "winner": [
            {
                "total_amount": -1.0,
                "home_team_score": 1.12,
                "away_team_score": 5.5
            }
        ],
        "first_blood": [
            {
                "total_amount": 1.0,
                "home_team_score": 1.57,
                "away_team_score": 2.25
            }
        ],
        "first_kill_baron": [
            {
                "total_amount": 1.0,
                "home_team_score": 1.25,
                "away_team_score": 3.75
            }
        ],
        "first_destroy_inhibitor": [
            {
                "total_amount": 1.0,
                "home_team_score": 1.14,
                "away_team_score": 5.0
            }
        ],
        "kill_handicap": [
            {
                "total_amount": 11.5,
                "home_team_score": 1.83,
                "away_team_score": 1.83
            }
        ],
        "total_kills": [
            {
                "total_amount": 24.5,
                "home_team_score": 1.8,
                "away_team_score": 1.9
            }
        ],
        "total_towers": [
            {
                "total_amount": 11.5,
                "home_team_score": 2.5,
                "away_team_score": 1.5
            }
        ],
        "tower_handicap": [],
        "first_tower": [],
        "total_dragons": [
            {
                "total_amount": 4.5,
                "home_team_score": 2.5,
                "away_team_score": 1.5
            }
        ],
        "first_dragon": [],
        "total_barons": [
            {
                "total_amount": 1.5,
                "home_team_score": 3.4,
                "away_team_score": 1.3
            }
        ],
        "total_inhibitors": [
            {
                "total_amount": 1.5,
                "home_team_score": 2.0,
                "away_team_score": 1.72
            }
        ],
        "game_duration": [
            {
                "total_amount": 30.5,
                "home_team_score": 1.83,
                "away_team_score": 1.83
            }
        ]
    },
    {
        "overview": {
            "game_date": 1706873400.0,
            "url": "https://www.bet365.com/#/AC/B151/C20930782/D19/E18901490/F19/",
            "league": "LOL - LCK Spring",
            "home_team": "Dplus KIA",
            "away_team": "Hanwha Life Esports"
        },
        "winner": [
            {
                "total_amount": -1.0,
                "home_team_score": 2.1,
                "away_team_score": 1.66
            }
        ],
        "first_blood": [
            {
                "total_amount": 1.0,
                "home_team_score": 1.9,
                "away_team_score": 1.8
            }
        ],
        "first_kill_baron": [
            {
                "total_amount": 1.0,
                "home_team_score": 2.0,
                "away_team_score": 1.72
            }
        ],
        "first_destroy_inhibitor": [
            {
                "total_amount": 1.0,
                "home_team_score": 2.1,
                "away_team_score": 1.66
            }
        ],
        "kill_handicap": [
            {
                "total_amount": 4.5,
                "home_team_score": 1.83,
                "away_team_score": 1.83
            }
        ],
        "total_kills": [
            {
                "total_amount": 20.5,
                "home_team_score": 1.9,
                "away_team_score": 1.8
            }
        ],
        "total_towers": [
            {
                "total_amount": 12.5,
                "home_team_score": 2.25,
                "away_team_score": 1.57
            }
        ],
        "tower_handicap": [],
        "first_tower": [],
        "total_dragons": [
            {
                "total_amount": 4.5,
                "home_team_score": 1.5,
                "away_team_score": 2.5
            }
        ],
        "first_dragon": [],
        "total_barons": [
            {
                "total_amount": 1.5,
                "home_team_score": 1.53,
                "away_team_score": 2.37
            }
        ],
        "total_inhibitors": [
            {
                "total_amount": 1.5,
                "home_team_score": 1.5,
                "away_team_score": 2.5
            }
        ],
        "game_duration": [
            {
                "total_amount": 33.5,
                "home_team_score": 1.83,
                "away_team_score": 1.83
            }
        ]
    },
    {
        "overview": {
            "game_date": 1706943600.0,
            "url": "https://www.bet365.com/#/AC/B151/C20930782/D19/E18901491/F19/",
            "league": "LOL - LCK Spring",
            "home_team": "DRX",
            "away_team": "KT Rolster"
        },
        "winner": [
            {
                "total_amount": -1.0,
                "home_team_score": 3.0,
                "away_team_score": 1.36
            }
        ],
        "first_blood": [
            {
                "total_amount": 1.0,
                "home_team_score": 2.0,
                "away_team_score": 1.72
            }
        ],
        "first_kill_baron": [
            {
                "total_amount": 1.0,
                "home_team_score": 2.5,
                "away_team_score": 1.5
            }
        ],
        "first_destroy_inhibitor": [
            {
                "total_amount": 1.0,
                "home_team_score": 2.75,
                "away_team_score": 1.4
            }
        ],
        "kill_handicap": [
            {
                "total_amount": 7.5,
                "home_team_score": 1.83,
                "away_team_score": 1.83
            }
        ],
        "total_kills": [
            {
                "total_amount": 23.5,
                "home_team_score": 1.83,
                "away_team_score": 1.83
            }
        ],
        "total_towers": [
            {
                "total_amount": 11.5,
                "home_team_score": 2.0,
                "away_team_score": 1.72
            }
        ],
        "tower_handicap": [],
        "first_tower": [],
        "total_dragons": [
            {
                "total_amount": 4.5,
                "home_team_score": 1.66,
                "away_team_score": 2.1
            }
        ],
        "first_dragon": [],
        "total_barons": [
            {
                "total_amount": 1.5,
                "home_team_score": 1.72,
                "away_team_score": 2.0
            }
        ],
        "total_inhibitors": [
            {
                "total_amount": 1.5,
                "home_team_score": 1.57,
                "away_team_score": 2.25
            }
        ],
        "game_duration": [
            {
                "total_amount": 32.5,
                "home_team_score": 1.83,
                "away_team_score": 1.83
            }
        ]
    },
    {
        "overview": {
            "game_date": 1706952600.0,
            "url": "https://www.bet365.com/#/AC/B151/C20930782/D19/E18901492/F19/",
            "league": "LOL - LCK Spring",
            "home_team": "OKSavingsBank BRION",
            "away_team": "T1"
        },
        "winner": [
            {
                "total_amount": -1.0,
                "home_team_score": 6.0,
                "away_team_score": 1.11
            }
        ],
        "first_blood": [
            {
                "total_amount": 1.0,
                "home_team_score": 2.25,
                "away_team_score": 1.57
            }
        ],
        "first_kill_baron": [
            {
                "total_amount": 1.0,
                "home_team_score": 3.75,
                "away_team_score": 1.25
            }
        ],
        "first_destroy_inhibitor": [
            {
                "total_amount": 1.0,
                "home_team_score": 5.0,
                "away_team_score": 1.14
            }
        ],
        "kill_handicap": [
            {
                "total_amount": 9.5,
                "home_team_score": 1.83,
                "away_team_score": 1.83
            }
        ],
        "total_kills": [
            {
                "total_amount": 22.5,
                "home_team_score": 1.83,
                "away_team_score": 1.83
            }
        ],
        "total_towers": [
            {
                "total_amount": 11.5,
                "home_team_score": 2.5,
                "away_team_score": 1.5
            }
        ],
        "tower_handicap": [],
        "first_tower": [],
        "total_dragons": [
            {
                "total_amount": 4.5,
                "home_team_score": 2.37,
                "away_team_score": 1.53
            }
        ],
        "first_dragon": [],
        "total_barons": [
            {
                "total_amount": 1.5,
                "home_team_score": 3.4,
                "away_team_score": 1.3
            }
        ],
        "total_inhibitors": [
            {
                "total_amount": 1.5,
                "home_team_score": 2.0,
                "away_team_score": 1.72
            }
        ],
        "game_duration": [
            {
                "total_amount": 30.5,
                "home_team_score": 1.83,
                "away_team_score": 1.83
            }
        ]
    },
    {
        "overview": {
            "game_date": 1707030000.0,
            "url": "https://www.bet365.com/#/AC/B151/C20930782/D19/E18901493/F19/",
            "league": "LOL - LCK Spring",
            "home_team": "Nongshim RedForce",
            "away_team": "Hanwha Life Esports"
        },
        "winner": [
            {
                "total_amount": -1.0,
                "home_team_score": 4.33,
                "away_team_score": 1.2
            }
        ],
        "first_blood": [
            {
                "total_amount": 1.0,
                "home_team_score": 2.2,
                "away_team_score": 1.61
            }
        ],
        "first_kill_baron": [
            {
                "total_amount": 1.0,
                "home_team_score": 3.25,
                "away_team_score": 1.33
            }
        ],
        "first_destroy_inhibitor": [
            {
                "total_amount": 1.0,
                "home_team_score": 4.0,
                "away_team_score": 1.22
            }
        ],
        "kill_handicap": [
            {
                "total_amount": 8.5,
                "home_team_score": 1.83,
                "away_team_score": 1.83
            }
        ],
        "total_kills": [
            {
                "total_amount": 21.5,
                "home_team_score": 1.83,
                "away_team_score": 1.83
            }
        ],
        "total_towers": [
            {
                "total_amount": 11.5,
                "home_team_score": 2.5,
                "away_team_score": 1.5
            }
        ],
        "tower_handicap": [],
        "first_tower": [],
        "total_dragons": [
            {
                "total_amount": 4.5,
                "home_team_score": 2.37,
                "away_team_score": 1.53
            }
        ],
        "first_dragon": [],
        "total_barons": [
            {
                "total_amount": 1.5,
                "home_team_score": 3.0,
                "away_team_score": 1.36
            }
        ],
        "total_inhibitors": [
            {
                "total_amount": 1.5,
                "home_team_score": 1.83,
                "away_team_score": 1.83
            }
        ],
        "game_duration": [
            {
                "total_amount": 30.5,
                "home_team_score": 1.83,
                "away_team_score": 1.83
            }
        ]
    },
    {
        "overview": {
            "game_date": 1707039000.0,
            "url": "https://www.bet365.com/#/AC/B151/C20930782/D19/E18901494/F19/",
            "league": "LOL - LCK Spring",
            "home_team": "FearX",
            "away_team": "Gen.G"
        },
        "winner": [
            {
                "total_amount": -1.0,
                "home_team_score": 4.33,
                "away_team_score": 1.2
            }
        ],
        "first_blood": [
            {
                "total_amount": 1.0,
                "home_team_score": 2.2,
                "away_team_score": 1.61
            }
        ],
        "first_kill_baron": [
            {
                "total_amount": 1.0,
                "home_team_score": 3.25,
                "away_team_score": 1.33
            }
        ],
        "first_destroy_inhibitor": [
            {
                "total_amount": 1.0,
                "home_team_score": 4.0,
                "away_team_score": 1.22
            }
        ],
        "kill_handicap": [
            {
                "total_amount": 9.5,
                "home_team_score": 1.83,
                "away_team_score": 1.83
            }
        ],
        "total_kills": [
            {
                "total_amount": 23.5,
                "home_team_score": 1.8,
                "away_team_score": 1.9
            }
        ],
        "total_towers": [
            {
                "total_amount": 11.5,
                "home_team_score": 2.25,
                "away_team_score": 1.57
            }
        ],
        "tower_handicap": [],
        "first_tower": [],
        "total_dragons": [
            {
                "total_amount": 4.5,
                "home_team_score": 2.5,
                "away_team_score": 1.5
            }
        ],
        "first_dragon": [],
        "total_barons": [
            {
                "total_amount": 1.5,
                "home_team_score": 3.0,
                "away_team_score": 1.36
            }
        ],
        "total_inhibitors": [
            {
                "total_amount": 1.5,
                "home_team_score": 2.0,
                "away_team_score": 1.72
            }
        ],
        "game_duration": [
            {
                "total_amount": 29.5,
                "home_team_score": 1.83,
                "away_team_score": 1.83
            }
        ]
    }
]